azarashi/__init__.py
azarashi/__main__.py
azarashi/network/__init__.py
azarashi/network/receiver.py
azarashi/network/transmitter.py
azarashi/qzss_dcr_lib/__init__.py
azarashi/qzss_dcr_lib/decoder/__init__.py
azarashi/qzss_dcr_lib/decoder/hex_qzss_dcr_decoder.py
azarashi/qzss_dcr_lib/decoder/net_qzss_dcr_decoder.py
azarashi/qzss_dcr_lib/decoder/nmea_qzss_dcr_decoder.py
azarashi/qzss_dcr_lib/decoder/qzss_dcr_decoder.py
azarashi/qzss_dcr_lib/decoder/qzss_dcr_decoder_base.py
azarashi/qzss_dcr_lib/decoder/qzss_dcr_decoder_jma.py
azarashi/qzss_dcr_lib/decoder/qzss_dcr_decoder_jma_ash_fall.py
azarashi/qzss_dcr_lib/decoder/qzss_dcr_decoder_jma_common.py
azarashi/qzss_dcr_lib/decoder/qzss_dcr_decoder_jma_earthquake_early_warning.py
azarashi/qzss_dcr_lib/decoder/qzss_dcr_decoder_jma_flood.py
azarashi/qzss_dcr_lib/decoder/qzss_dcr_decoder_jma_hypocenter.py
azarashi/qzss_dcr_lib/decoder/qzss_dcr_decoder_jma_marine.py
azarashi/qzss_dcr_lib/decoder/qzss_dcr_decoder_jma_nankai_trough_earthquake.py
azarashi/qzss_dcr_lib/decoder/qzss_dcr_decoder_jma_northwest_pacific_tsunami.py
azarashi/qzss_dcr_lib/decoder/qzss_dcr_decoder_jma_seismic_intensity.py
azarashi/qzss_dcr_lib/decoder/qzss_dcr_decoder_jma_tsunami.py
azarashi/qzss_dcr_lib/decoder/qzss_dcr_decoder_jma_typhoon.py
azarashi/qzss_dcr_lib/decoder/qzss_dcr_decoder_jma_volcano.py
azarashi/qzss_dcr_lib/decoder/qzss_dcr_decoder_jma_weather.py
azarashi/qzss_dcr_lib/decoder/qzss_dcx_decoder.py
azarashi/qzss_dcr_lib/decoder/ublox_qzss_dcr_decoder.py
azarashi/qzss_dcr_lib/definition/__init__.py
azarashi/qzss_dcr_lib/definition/nmea_qzss_dcr_message_header.py
azarashi/qzss_dcr_lib/definition/qzss_dcr_definition.py
azarashi/qzss_dcr_lib/definition/qzss_dcr_jma_ash_fall_warning_code.py
azarashi/qzss_dcr_lib/definition/qzss_dcr_jma_coastal_region.py
azarashi/qzss_dcr_lib/definition/qzss_dcr_jma_disaster_category.py
azarashi/qzss_dcr_lib/definition/qzss_dcr_jma_eew_forecast_region.py
azarashi-0.15.1.dist-info/licenses/LICENSE
azarashi-0.15.1.dist-info/METADATA
azarashi-0.15.1.dist-info/WHEEL
azarashi-0.15.1.dist-info/entry_points.txt
azarashi-0.15.1.dist-info/top_level.txt
azarashi-0.15.1.dist-info/RECORD
