Metadata-Version: 2.4
Name: azarashi
Version: 0.15.1
Summary: QZSS DCR Decoder
Home-page: https://github.com/nbtk/azarashi
Author: nbtk
License: MIT
Classifier: Development Status :: 4 - Beta
Classifier: Programming Language :: Python :: 3
Classifier: License :: OSI Approved :: MIT License
Requires-Python: >=3.9
License-File: LICENSE
Dynamic: author
Dynamic: classifier
Dynamic: description
Dynamic: description-content-type
Dynamic: home-page
Dynamic: license
Dynamic: license-file
Dynamic: requires-python
Dynamic: summary
